dataobjtools/selector.py
dataobjtools-0.1.3.dist-info/WHEEL
dataobjtools-0.1.3.dist-info/METADATA
dataobjtools-0.1.3.dist-info/RECORD
