Metadata-Version: 2.1
Name: dataobjtools
Version: 0.1.3
Summary: Data Object helpers for Dicts and Lists for searching, managing,  manipulating etc
License: MIT
Author: pub12
Author-email: pubudu79@gmail.com
Requires-Python: >=3.8,<4.0
Classifier: License :: OSI Approved :: MIT License
Classifier: Programming Language :: Python :: 3
Classifier: Programming Language :: Python :: 3.10
Classifier: Programming Language :: Python :: 3.8
Classifier: Programming Language :: Python :: 3.9
